ioc_hunter/__init__.py
ioc_hunter/ioc_hunter.py
ioc_hunter/ioc_types.py
ioc_hunter/data/tld_list.txt
ioc_hunter/models/ioc_model/config.cfg
ioc_hunter/models/ioc_model/meta.json
ioc_hunter/models/ioc_model/tokenizer
ioc_hunter/models/ioc_model/ner/cfg
ioc_hunter/models/ioc_model/ner/model
ioc_hunter/models/ioc_model/ner/moves
ioc_hunter/models/ioc_model/tok2vec/cfg
ioc_hunter/models/ioc_model/tok2vec/model
ioc_hunter/models/ioc_model/vocab/key2row
ioc_hunter/models/ioc_model/vocab/lookups.bin
ioc_hunter/models/ioc_model/vocab/strings.json
ioc_hunter/models/ioc_model/vocab/vectors
ioc_hunter-1.4.2.dist-info/licenses/LICENSE
ioc_hunter-1.4.2.dist-info/METADATA
ioc_hunter-1.4.2.dist-info/WHEEL
ioc_hunter-1.4.2.dist-info/top_level.txt
ioc_hunter-1.4.2.dist-info/RECORD
