Metadata-Version: 2.4
Name: ioc-hunter
Version: 1.4.2
Summary: Extract IOCs from text.
Home-page: https://github.com/swimlane/ioc-hunter
Author: Swimlane
Author-email: info@swimlane.com
Project-URL: Bug Tracker, https://github.com/swimlane/ioc-hunter/issues
Classifier: Programming Language :: Python :: 3
Classifier: License :: OSI Approved :: MIT License
Classifier: Operating System :: OS Independent
Requires-Python: >=3.7
License-File: LICENSE
Requires-Dist: ipaddress<2,>=1.0.23
Requires-Dist: iocextract==1.13.1
Requires-Dist: spacy<4,>=3.4.1
Requires-Dist: tldextract<6,>=5.2.0
Dynamic: license-file
